diffuse_neutrino_flux/__init__.py
diffuse_neutrino_flux/data/cascades20_contour68.csv
diffuse_neutrino_flux/data/gp_pi0_contour68.csv
diffuse_neutrino_flux/data/hese21_contour68.csv
diffuse_neutrino_flux/data/joint15_contour68.csv
diffuse_neutrino_flux/data/joint23_spl_contour68.csv
diffuse_neutrino_flux/data/measurements.json
diffuse_neutrino_flux/data/ngc1068_contour68.csv
diffuse_neutrino_flux/data/nt22_contour68.csv
diffuse_neutrino_flux/data/txs0506_contour68.csv
diffuse_neutrino_flux/spectrum.py
diffuse_neutrino_flux-0.3.0.dist-info/METADATA
diffuse_neutrino_flux-0.3.0.dist-info/WHEEL
diffuse_neutrino_flux-0.3.0.dist-info/RECORD
