Metadata-Version: 2.3
Name: diffuse-neutrino-flux
Version: 0.3.0
Summary: Lightweight package to plot diffuse neutrino flux measurements
License: MIT
Author: Jannis Necker
Author-email: jannis.necker@gmail.com
Requires-Python: >=3.10
Classifier: License :: OSI Approved :: MIT License
Classifier: Programming Language :: Python :: 3
Classifier: Programming Language :: Python :: 3.10
Classifier: Programming Language :: Python :: 3.11
Classifier: Programming Language :: Python :: 3.12
Classifier: Programming Language :: Python :: 3.13
Provides-Extra: dev
Requires-Dist: matplotlib (>=3.3.0)
Requires-Dist: mypy (>=1.15.0,<2.0.0) ; extra == "dev"
Requires-Dist: numpy (>=1.20.0)
Requires-Dist: pandas (>=2.0.0,<3.0.0)
Requires-Dist: pytest (>=8.3.5,<9.0.0) ; extra == "dev"
Requires-Dist: ruff (>=0.11.7) ; extra == "dev"
Project-URL: Repository, https://github.com/JannisNe/diffuse_neutrino_flux
